adam_signurl/__init__.py
adam_signurl/adam_signurl.py
adam_signurl-0.1.6.dist-info/METADATA
adam_signurl-0.1.6.dist-info/WHEEL
adam_signurl-0.1.6.dist-info/RECORD
