Metadata-Version: 2.1
Name: adam-signurl
Version: 0.1.6
Summary: Libreria para firmar archivos en GCS
Author: Eduardo Pagnone
Author-email: eduardopagnone@gmail.com
Requires-Python: >=3.7,<4.0
Classifier: Programming Language :: Python :: 3
Classifier: Programming Language :: Python :: 3.7
Classifier: Programming Language :: Python :: 3.8
Classifier: Programming Language :: Python :: 3.9
Classifier: Programming Language :: Python :: 3.10
Classifier: Programming Language :: Python :: 3.11
Requires-Dist: adam-credmanager (>=0.1.3,<0.2.0)
Requires-Dist: google-auth (>=2,<3)
Requires-Dist: google-cloud-secret-manager (>=2.16,<3.0)
Requires-Dist: six (>=1.16.0,<2.0.0)
